hoopstats/__init__.py
hoopstats/services/__init__.py
hoopstats/services/player_scraper.py
hoopstats/services/team_scraper.py
hoopstats/test.py
hoopstats/utils/__init__.py
hoopstats/utils/decorator_utils.py
hoopstats/utils/pandas_utils.py
hoopstats/utils/players_utils.py
hoopstats/utils/request_utils.py
hoopstats/utils/team_utils.py
hoopstats-0.1.5.dist-info/LICENSE
hoopstats-0.1.5.dist-info/METADATA
hoopstats-0.1.5.dist-info/WHEEL
hoopstats-0.1.5.dist-info/RECORD
