Metadata-Version: 2.1
Name: hoopstats
Version: 0.1.5
Summary: A Python package for scraping NBA data from Basketball Reference.
License: MIT
Author: Calvin Min
Author-email: Calvinjmin@gmail.com
Requires-Python: >=3.11,<4.0
Classifier: License :: OSI Approved :: MIT License
Classifier: Programming Language :: Python :: 3
Classifier: Programming Language :: Python :: 3.11
Classifier: Programming Language :: Python :: 3.12
Requires-Dist: beautifulsoup4 (>=4.12.3,<5.0.0)
Requires-Dist: html5lib (>=1.1,<2.0)
Requires-Dist: lxml (>=5.3.0,<6.0.0)
Requires-Dist: matplot (>=0.1.9,<0.2.0)
Requires-Dist: pandas (>=2.2.2,<3.0.0)
Requires-Dist: rapidfuzz (>=3.9.7,<4.0.0)
Requires-Dist: requests (>=2.32.3,<3.0.0)
Requires-Dist: selenium (>=4.24.0,<5.0.0)
